Workbook

Sheet Summary
A1: LNG Facilities — Consolidated Summary
A2: Generated: 2026-06-22T12:42:46
A3: Values pull live from the underlying tabs — edit cells there and the Summary updates on recalc.
A5: Overall
A6: Liquefaction facilities tracked | B6: =COUNTA('Liquefaction — Operational'!A:A) + COUNTA('Liquefaction — Upcoming'!A:A) - 2 -> 110
A7: Operational trains | B7: =COUNTA('Liquefaction — Operational'!A:A) - 1 -> 79
A8: Upcoming (planned/FID/construction/commissioning) | B8: =COUNTIF('Liquefaction — Upcoming'!G:G,"planned") + COUNTIF('Liquefaction — Upcoming'!G:G,"FID") + COUNTIF('Liquefaction — Upcoming'!G:G,"construction") + COUNTIF('Liquefaction — Upcoming'!G:G,"commissioning") -> 27
A9: Mothballed / paused / retired | B9: =COUNTIF('Liquefaction — Upcoming'!G:G,"mothballed") + COUNTIF('Liquefaction — Upcoming'!G:G,"paused") + COUNTIF('Liquefaction — Upcoming'!G:G,"retired") -> 4
A10: Regasification terminals tracked | B10: =COUNTA('Regasification — Operational'!A:A) + COUNTA('Regasification — Upcoming'!A:A) - 2 -> 68
A11: Operational | B11: =COUNTA('Regasification — Operational'!A:A) - 1 -> 66
A12: Upcoming | B12: =COUNTA('Regasification — Upcoming'!A:A) - 1 -> 2
A13: Active disruptions (end_date blank) | B13: =COUNTA(Disruptions!A:A) - COUNTA(Disruptions!E:E) -> 6
A15: Capacity (MTPA)
A16: Operational liquefaction nameplate (MTPA) | B16: =SUM('Liquefaction — Operational'!H:H) -> 416.75
A17: Operational liquefaction effective (MTPA) | B17: =SUM('Liquefaction — Operational'!I:I) -> 393.95
A18: Upcoming liquefaction nameplate (MTPA) | B18: =SUMIFS('Liquefaction — Upcoming'!H:H,'Liquefaction — Upcoming'!G:G,"planned") + SUMIFS('Liquefaction — Upcoming'!H:H,'Liquefaction — Upcoming'!G:G,"FID") + SUMIFS('Liquefaction — Upcoming'!H:H,'Liquefaction — Upcoming'!G:G,"construction") + SUMIFS('Liquefaction — Upcoming'!H:H,'Liquefaction — Upcoming'!G:G,"commissioning") -> 180.73
A19: Operational regas send-out (MTPA equiv) | B19: =SUM('Regasification — Operational'!I:I) -> 519
A20: Upcoming regas send-out (MTPA equiv) | B20: =SUM('Regasification — Upcoming'!I:I) -> 16.1
A22: Operational Liquefaction by Region
A23: Region | B23: Nameplate (MTPA) | C23: Effective (MTPA) | D23: Trains
A24: Australia | B24: =SUMIFS('Liquefaction — Operational'!H:H,'Liquefaction — Operational'!C:C,"Australia") -> 91.4 | C24: =SUMIFS('Liquefaction — Operational'!I:I,'Liquefaction — Operational'!C:C,"Australia") -> 88.6 | D24: =COUNTIF('Liquefaction — Operational'!C:C,"Australia") -> 22
A25: Europe | B25: =SUMIFS('Liquefaction — Operational'!H:H,'Liquefaction — Operational'!C:C,"Europe") -> 4.3 | C25: =SUMIFS('Liquefaction — Operational'!I:I,'Liquefaction — Operational'!C:C,"Europe") -> 4 | D25: =COUNTIF('Liquefaction — Operational'!C:C,"Europe") -> 1
A26: Latin America | B26: =SUMIFS('Liquefaction — Operational'!H:H,'Liquefaction — Operational'!C:C,"Latin America") -> 12.2 | C26: =SUMIFS('Liquefaction — Operational'!I:I,'Liquefaction — Operational'!C:C,"Latin America") -> 10.4 | D26: =COUNTIF('Liquefaction — Operational'!C:C,"Latin America") -> 3
A27: MENA | B27: =SUMIFS('Liquefaction — Operational'!H:H,'Liquefaction — Operational'!C:C,"MENA") -> 86.3 | C27: =SUMIFS('Liquefaction — Operational'!I:I,'Liquefaction — Operational'!C:C,"MENA") -> 84.1 | D27: =COUNTIF('Liquefaction — Operational'!C:C,"MENA") -> 10
A28: North America | B28: =SUMIFS('Liquefaction — Operational'!H:H,'Liquefaction — Operational'!C:C,"North America") -> 99.55 | C28: =SUMIFS('Liquefaction — Operational'!I:I,'Liquefaction — Operational'!C:C,"North America") -> 105.25 | D28: =COUNTIF('Liquefaction — Operational'!C:C,"North America") -> 20
A29: Russia/Arctic | B29: =SUMIFS('Liquefaction — Operational'!H:H,'Liquefaction — Operational'!C:C,"Russia/Arctic") -> 27 | C29: =SUMIFS('Liquefaction — Operational'!I:I,'Liquefaction — Operational'!C:C,"Russia/Arctic") -> 24.9 | D29: =COUNTIF('Liquefaction — Operational'!C:C,"Russia/Arctic") -> 6
A30: SE Asia | B30: =SUMIFS('Liquefaction — Operational'!H:H,'Liquefaction — Operational'!C:C,"SE Asia") -> 67.9 | C30: =SUMIFS('Liquefaction — Operational'!I:I,'Liquefaction — Operational'!C:C,"SE Asia") -> 50.5 | D30: =COUNTIF('Liquefaction — Operational'!C:C,"SE Asia") -> 11
A31: Sub-Saharan Africa | B31: =SUMIFS('Liquefaction — Operational'!H:H,'Liquefaction — Operational'!C:C,"Sub-Saharan Africa") -> 28.1 | C31: =SUMIFS('Liquefaction — Operational'!I:I,'Liquefaction — Operational'!C:C,"Sub-Saharan Africa") -> 26.2 | D31: =COUNTIF('Liquefaction — Operational'!C:C,"Sub-Saharan Africa") -> 6

Sheet Liquefaction — Operational
A1: Facility ID | B1: Country | C1: Region | D1: Facility | E1: Operator | F1: Train | G1: Status | H1: Nameplate (MTPA) | I1: Effective (MTPA) | J1: FID | K1: Start / COD | L1: Ramp-up | M1: Feedgas | N1: Offtake | O1: Source | P1: Updated | Q1: Notes
A2: AU-APLNG-T1 | B2: Australia | C2: Australia | D2: Australia Pacific LNG | E2: ConocoPhillips/Origin/Sinopec | F2: T1 | G2: operational | H2: 4.5 | I2: 4.5 | J2: 2011-07-28 | K2: 2015-12-17 | L2: immediate | M2: Queensland CSG | N2: Sinopec/Kansai Electric | O2: Origin/COP releases | P2: 2026-06-01 | Q2: Curtis Island Gladstone
A3: AU-APLNG-T2 | B3: Australia | C3: Australia | D3: Australia Pacific LNG | E3: ConocoPhillips/Origin/Sinopec | F3: T2 | G3: operational | H3: 4.5 | I3: 4.5 | J3: 2011-07-28 | K3: 2016-10-13 | L3: immediate | M3: Queensland CSG | N3: Sinopec | O3: Same | P3: 2026-06-01
A4: AU-GLNG-T1 | B4: Australia | C4: Australia | D4: Gladstone LNG | E4: Santos/Petronas/Total/KOGAS | F4: T1 | G4: operational | H4: 3.9 | I4: 3.6 | J4: 2010-12-13 | K4: 2015-10-13 | L4: immediate | M4: Queensland CSG | N4: KOGAS/Petronas | O4: Santos | P4: 2026-06-01 | Q4: Curtis Island; feedgas constrained
A5: AU-GLNG-T2 | B5: Australia | C5: Australia | D5: Gladstone LNG | E5: Santos/Petronas/Total/KOGAS | F5: T2 | G5: operational | H5: 3.9 | I5: 3.6 | J5: 2010-12-13 | K5: 2016-05-01 | L5: immediate | M5: Same | N5: Same | O5: Santos | P5: 2026-06-01
A6: AU-GORGON-T1 | B6: Australia | C6: Australia | D6: Gorgon LNG | E6: Chevron/ExxonMobil/Shell | F6: T1 | G6: operational | H6: 5.2 | I6: 5 | J6: 2009-09-14 | K6: 2016-03-21 | L6: immediate | M6: Gorgon/Jansz-Io | N6: Long-term portfolio | O6: Chevron | P6: 2026-06-01 | Q6: Barrow Island
A7: AU-GORGON-T2 | B7: Australia | C7: Australia | D7: Gorgon LNG | E7: Chevron/ExxonMobil/Shell | F7: T2 | G7: operational | H7: 5.2 | I7: 5 | J7: 2009-09-14 | K7: 2016-10-15 | L7: immediate | M7: Same | N7: Same | O7: Chevron | P7: 2026-06-01
A8: AU-GORGON-T3 | B8: Australia | C8: Australia | D8: Gorgon LNG | E8: Chevron/ExxonMobil/Shell | F8: T3 | G8: operational | H8: 5.2 | I8: 5 | J8: 2009-09-14 | K8: 2017-03-01 | L8: immediate | M8: Same | N8: Same | O8: Chevron | P8: 2026-06-01
A9: AU-ICHTHYS-T1 | B9: Australia | C9: Australia | D9: Ichthys LNG | E9: INPEX/TotalEnergies | F9: T1 | G9: operational | H9: 4.45 | I9: 4.4 | J9: 2012-01-13 | K9: 2018-10-09 | L9: immediate | M9: Ichthys field | N9: JERA/Tokyo Gas/Osaka Gas portfolio | O9: INPEX | P9: 2026-06-01 | Q9: Darwin
A10: AU-ICHTHYS-T2 | B10: Australia | C10: Australia | D10: Ichthys LNG | E10: INPEX/TotalEnergies | F10: T2 | G10: operational | H10: 4.45 | I10: 4.4 | J10: 2012-01-13 | K10: 2018-12-30 | L10: immediate | M10: Same | N10: Same | O10: INPEX | P10: 2026-06-01
A11: AU-NWS-T1 | B11: Australia | C11: Australia | D11: North West Shelf | E11: Woodside/BP/Chevron/Shell/MIMI | F11: T1 | G11: operational | H11: 2.5 | I11: 2.4 | J11: 1980-01-01 | K11: 1989-08-15 | L11: immediate | M11: Carnarvon Basin | N11: Japanese utilities portfolio | O11: Woodside reports | P11: 2026-06-01 | Q11: Original 1989 train
A12: AU-NWS-T2 | B12: Australia | C12: Australia | D12: North West Shelf | E12: Woodside/BP/Chevron/Shell/MIMI | F12: T2 | G12: operational | H12: 2.5 | I12: 2.4 | J12: 1980-01-01 | K12: 1989-08-15 | L12: immediate | M12: Carnarvon Basin | N12: Same | O12: Woodside | P12: 2026-06-01
A13: AU-NWS-T3 | B13: Australia | C13: Australia | D13: North West Shelf | E13: Woodside/BP/Chevron/Shell/MIMI | F13: T3 | G13: operational | H13: 2.5 | I13: 2.4 | J13: 1989-01-01 | K13: 1992-10-01 | L13: immediate | M13: Carnarvon Basin | N13: Same | O13: Woodside | P13: 2026-06-01
A14: AU-NWS-T4 | B14: Australia | C14: Australia | D14: North West Shelf | E14: Woodside/BP/Chevron/Shell/MIMI | F14: T4 | G14: operational | H14: 4.4 | I14: 4.3 | J14: 2001-01-01 | K14: 2004-09-01 | L14: immediate | M14: Carnarvon Basin | N14: Same | O14: Woodside | P14: 2026-06-01
A15: AU-NWS-T5 | B15: Australia | C15: Australia | D15: North West Shelf | E15: Woodside/BP/Chevron/Shell/MIMI | F15: T5 | G15: operational | H15: 4.4 | I15: 4.3 | J15: 2005-01-01 | K15: 2008-09-01 | L15: immediate | M15: Carnarvon Basin (declining; future Browse/Scarborough backfill) | N15: Same | O15: Woodside | P15: 2026-06-01 | Q15: Feedgas constrained; backfill key
A16: AU-PLUTO-T1 | B16: Australia | C16: Australia | D16: Pluto LNG | E16: Woodside | F16: T1 | G16: operational | H16: 4.9 | I16: 4.8 | J16: 2007-07-20 | K16: 2012-04-22 | L16: immediate | M16: Pluto field | N16: Tokyo Gas/Kansai Electric | O16: Woodside | P16: 2026-06-01
A17: AU-PRELUDE-FLNG | B17: Australia | C17: Australia | D17: Prelude FLNG | E17: Shell/INPEX/KOGAS/CPC | F17: FLNG | G17: operational | H17: 3.6 | I17: 3.2 | J17: 2011-05-20 | K17: 2019-06-25 | L17: slow ramp | M17: Prelude field | N17: Shell offtake | O17: Shell | P17: 2026-06-01 | Q17: FLNG; ongoing operational issues
A18: AU-QCLNG-T1 | B18: Australia | C18: Australia | D18: Queensland Curtis LNG | E18: Shell (BG legacy) | F18: T1 | G18: operational | H18: 4 | I18: 4 | J18: 2010-10-30 | K18: 2014-12-31 | L18: immediate | M18: Queensland CSG | N18: Shell portfolio | O18: Shell | P18: 2026-06-01
A19: AU-QCLNG-T2 | B19: Australia | C19: Australia | D19: Queensland Curtis LNG | E19: Shell (BG legacy) | F19: T2 | G19: operational | H19: 4 | I19: 4 | J19: 2010-10-30 | K19: 2015-09-30 | L19: immediate | M19: Same | N19: Same | O19: Shell | P19: 2026-06-01
A20: AU-WHEATSTONE-T1 | B20: Australia | C20: Australia | D20: Wheatstone LNG | E20: Chevron/Kuwait Foreign/Woodside/JERA/PE Wheatstone | F20: T1 | G20: operational | H20: 4.45 | I20: 4.4 | J20: 2011-09-27 | K20: 2017-10-09 | L20: immediate | M20: Wheatstone/Iago | N20: Long-term portfolio | O20: Chevron | P20: 2026-06-01
A21: AU-WHEATSTONE-T2 | B21: Australia | C21: Australia | D21: Wheatstone LNG | E21: Chevron/Kuwait Foreign/Woodside/JERA/PE Wheatstone | F21: T2 | G21: operational | H21: 4.45 | I21: 4.4 | J21: 2011-09-27 | K21: 2018-06-22 | L21: immediate | M21: Same | N21: Same | O21: Chevron | P21: 2026-06-01
A22: PG-PNGLNG-T1 | B22: Papua New Guinea | C22: Australia | D22: PNG LNG | E22: ExxonMobil/Oil Search/Santos/Kumul/MRDC/JX Nippon | F22: T1 | G22: operational | H22: 4.2 | I22: 4 | J22: 2009-12-08 | K22: 2014-04-25 | L22: immediate | M22: PNG Highlands | N22: JERA/Osaka Gas/Sinopec/CPC | O22: ExxonMobil | P22: 2026-06-01
A23: PG-PNGLNG-T2 | B23: Papua New Guinea | C23: Australia | D23: PNG LNG | E23: ExxonMobil/Oil Search/Santos/Kumul/MRDC/JX Nippon | F23: T2 | G23: operational | H23: 4.2 | I23: 4 | J23: 2009-12-08 | K23: 2014-07-15 | L23: immediate | M23: Same | N23: Same | O23: ExxonMobil | P23: 2026-06-01 | Q23: Expansion ('P'nyang') project in study
A24: NO-SNOHVIT | B24: Norway | C24: Europe | D24: Snøhvit LNG (Hammerfest) | E24: Equinor | F24: single | G24: operational | H24: 4.3 | I24: 4 | J24: 2002-03-23 | K24: 2007-09-01 | L24: immediate | M24: Snøhvit field | N24: Iberdrola/Total/RWE legacy | O24: Equinor | P24: 2026-06-01 | Q24: Hammerfest LNG; key European supply
A25: TT-ATLANTIC-T2 | B25: Trinidad and Tobago | C25: Latin America | D25: Atlantic LNG | E25: Shell/BP/NGC/CIC | F25: T2 | G25: operational | H25: 3.5 | I25: 3 | J25: 1995-01-01 | K25: 2002-08-01 | L25: immediate | M25: Trinidad | N25: Same | O25: Atlantic LNG | P25: 2026-06-01 | Q25: Feedgas constrained
A26: TT-ATLANTIC-T3 | B26: Trinidad and Tobago | C26: Latin America | D26: Atlantic LNG | E26: Shell/BP/NGC/CIC | F26: T3 | G26: operational | H26: 3.5 | I26: 3 | J26: 1995-01-01 | K26: 2003-04-25 | L26: immediate | M26: Trinidad | N26: Same | O26: Atlantic LNG | P26: 2026-06-01
A27: TT-ATLANTIC-T4 | B27: Trinidad and Tobago | C27: Latin America | D27: Atlantic LNG | E27: Shell/BP/NGC/CIC | F27: T4 | G27: operational | H27: 5.2 | I27: 4.4 | J27: 2002-01-01 | K27: 2005-12-28 | L27: immediate | M27: Trinidad | N27: Same | O27: Atlantic LNG | P27: 2026-06-01 | Q27: Largest train; feedgas constrained
A28: EG-DAMIETTA | B28: Egypt | C28: MENA | D28: Damietta LNG | E28: SEGAS (Eni/EGAS/EGPC) | F28: T1 | G28: operational | H28: 5 | I28: 4 | J28: 1998-01-01 | K28: 2005-01-01 | L28: immediate | M28: Egyptian offshore (Zohr/WDDM) | N28: Portfolio | O28: Eni | P28: 2026-06-01 | Q28: Restarted 2021 after 8-year halt; intermittent
A29: EG-IDKU-T1 | B29: Egypt | C29: MENA | D29: Egyptian LNG (Idku) | E29: Shell/Petronas/EGAS/EGPC | F29: T1 | G29: operational | H29: 3.6 | I29: 3 | J29: 2001-01-01 | K29: 2005-05-13 | L29: immediate | M29: WDDM/Egyptian offshore | N29: Portfolio | O29: Shell | P29: 2026-06-01
A30: EG-IDKU-T2 | B30: Egypt | C30: MENA | D30: Egyptian LNG (Idku) | E30: Shell/Petronas/EGAS/EGPC | F30: T2 | G30: operational | H30: 3.6 | I30: 3 | J30: 2001-01-01 | K30: 2005-09-25 | L30: immediate | M30: Same | N30: Same | O30: Shell | P30: 2026-06-01 | Q30: Frequently curtailed by domestic demand
A31: QA-QATARENERGY-QG1 | B31: Qatar | C31: MENA | D31: Qatargas 1 | E31: QatarEnergy LNG | F31: T1-T2 | G31: operational | H31: 6.6 | I31: 6.6 | J31: 1992-01-01 | K31: 1997-12-15 | L31: immediate | M31: North Field | N31: JERA/Tokyo Gas/Chubu Electric (legacy long-term) | O31: QatarEnergy releases | P31: 2026-06-01 | Q31: Two trains aggregated; longest-running Qatari LNG
A32: QA-QATARENERGY-QG2 | B32: Qatar | C32: MENA | D32: Qatargas 2 | E32: QatarEnergy LNG | F32: T4-T5 | G32: operational | H32: 15.6 | I32: 15.6 | J32: 2003-01-01 | K32: 2009-04-06 | L32: immediate | M32: North Field | N32: ExxonMobil/Total/Sinopec portfolio | O32: QatarEnergy | P32: 2026-06-01 | Q32: Two megatrains 7.8 MTPA each
A33: QA-QATARENERGY-QG3 | B33: Qatar | C33: MENA | D33: Qatargas 3 | E33: QatarEnergy LNG | F33: T6 | G33: operational | H33: 7.8 | I33: 7.8 | J33: 2005-01-01 | K33: 2010-11-15 | L33: immediate | M33: North Field | N33: ConocoPhillips/Mitsui | O33: QatarEnergy | P33: 2026-06-01 | Q33: Single megatrain
A34: QA-QATARENERGY-QG4 | B34: Qatar | C34: MENA | D34: Qatargas 4 | E34: QatarEnergy LNG | F34: T7 | G34: operational | H34: 7.8 | I34: 7.8 | J34: 2005-01-01 | K34: 2011-02-15 | L34: immediate | M34: North Field | N34: Shell | O34: QatarEnergy | P34: 2026-06-01
A35: QA-QATARENERGY-RG1 | B35: Qatar | C35: MENA | D35: RasGas 1 | E35: QatarEnergy LNG | F35: T1-T2 | G35: operational | H35: 6.6 | I35: 6.6 | J35: 1996-01-01 | K35: 1999-08-04 | L35: immediate | M35: North Field | N35: KOGAS/POSCO | O35: QatarEnergy | P35: 2026-06-01 | Q35: Merged into QatarEnergy LNG
A36: QA-QATARENERGY-RG2 | B36: Qatar | C36: MENA | D36: RasGas 2 | E36: QatarEnergy LNG | F36: T3-T4-T5 | G36: operational | H36: 14.1 | I36: 14.1 | J36: 2002-01-01 | K36: 2004-05-15 | L36: Y1-Y3 staggered start 2004-2007 | M36: North Field | N36: Distrigas/Edison/India Petronet | O36: QatarEnergy | P36: 2026-06-01 | Q36: 3 trains; mid-size
A37: QA-QATARENERGY-RG3 | B37: Qatar | C37: MENA | D37: RasGas 3 | E37: QatarEnergy LNG | F37: T6-T7 | G37: operational | H37: 15.6 | I37: 15.6 | J37: 2005-01-01 | K37: 2009-10-15 | L37: Trains 2009 and 2010 | M37: North Field | N37: ExxonMobil offtake | O37: QatarEnergy | P37: 2026-06-01 | Q37: 2 megatrains
A38: CA-LNGCANADA-T1 | B38: Canada | C38: North America | D38: LNG Canada Phase 1 | E38: Shell/PetroChina/Mitsubishi/MOGAS/KOGAS/Petronas | F38: T1 | G38: operational | H38: 7 | I38: 7 | J38: 2018-10-01 | K38: 2025-06-29 | L38: Y1:80%;Y2:100% | M38: Montney basin | N38: JV offtake by shareholders | O38: Shell press release June 2025 | P38: 2026-06-01 | Q38: First cargo June 2025
A39: CA-LNGCANADA-T2 | B39: Canada | C39: North America | D39: LNG Canada Phase 1 | E39: Shell/PetroChina/Mitsubishi/MOGAS/KOGAS/Petronas | F39: T2 | G39: operational | H39: 7 | I39: 7 | J39: 2018-10-01 | K39: 2026-03-01 | L39: Y1:80%;Y2:100% | M39: Montney | N39: Same JV | O39: Shell releases; giignl.org LNG Canada T2 production; lngcanada.ca; argusmedia.com | P39: 2026-06-22 | Q39: First LNG Nov 2025; COD spring 2026 per operator; commercial operations achieved ~Q1 2026
A40: US-CALCASIEU | B40: USA | C40: North America | D40: Calcasieu Pass | E40: Venture Global LNG | F40: Modular T1-T18 | G40: operational | H40: 10 | I40: 10 | J40: 2019-08-19 | K40: 2022-03-01 | L40: immediate | M40: US Gulf | N40: Portfolio + Shell/BP/EDF/Galp/Repsol/PGNiG | O40: VG SEC filings | P40: 2026-06-01 | Q40: 18 modular trains 0.55 MTPA each; commercial ops disputed by offtakers
A41: US-CAMERON-T1 | B41: USA | C41: North America | D41: Cameron LNG | E41: Sempra Infrastructure | F41: T1 | G41: operational | H41: 4 | I41: 4.5 | J41: 2014-08-12 | K41: 2019-05-15 | L41: immediate | M41: US Gulf | N41: Mitsubishi/Mitsui/TotalEnergies/Sempra | O41: Sempra 10-K | P41: 2026-06-01
A42: US-CAMERON-T2 | B42: USA | C42: North America | D42: Cameron LNG | E42: Sempra Infrastructure | F42: T2 | G42: operational | H42: 4 | I42: 4.5 | J42: 2014-08-12 | K42: 2020-02-14 | L42: immediate | M42: US Gulf | N42: Same | O42: Sempra 10-K | P42: 2026-06-01
A43: US-CAMERON-T3 | B43: USA | C43: North America | D43: Cameron LNG | E43: Sempra Infrastructure | F43: T3 | G43: operational | H43: 4 | I43: 4.5 | J43: 2014-08-12 | K43: 2020-08-10 | L43: immediate | M43: US Gulf | N43: Same | O43: Sempra 10-K | P43: 2026-06-01
A44: US-CORPUSCHRISTI-T1 | B44: USA | C44: North America | D44: Corpus Christi | E44: Cheniere Energy | F44: T1 | G44: operational | H44: 4.5 | I44: 5 | J44: 2015-05-13 | K44: 2019-05-22 | L44: immediate | M44: US shale | N44: Portfolio | O44: Cheniere 10-K | P44: 2026-06-01
A45: US-CORPUSCHRISTI-T2 | B45: USA | C45: North America | D45: Corpus Christi | E45: Cheniere Energy | F45: T2 | G45: operational | H45: 4.5 | I45: 5 | J45: 2015-05-13 | K45: 2019-09-30 | L45: immediate | M45: US shale | N45: Portfolio | O45: Cheniere 10-K | P45: 2026-06-01
A46: US-CORPUSCHRISTI-T3 | B46: USA | C46: North America | D46: Corpus Christi | E46: Cheniere Energy | F46: T3 | G46: operational | H46: 4.5 | I46: 5 | J46: 2018-05-09 | K46: 2021-03-26 | L46: immediate | M46: US shale | N46: Portfolio | O46: Cheniere 10-K | P46: 2026-06-01
A47: US-COVEPOINT | B47: USA | C47: North America | D47: Cove Point | E47: Berkshire Hathaway Energy | F47: single | G47: operational | H47: 5.25 | I47: 5.25 | J47: 2014-03-31 | K47: 2018-04-04 | L47: immediate | M47: Marcellus | N47: GAIL/Sumitomo (Tokyo Gas + Kansai Electric) | O47: Dominion (legacy) + BHE filings | P47: 2026-06-01
A48: US-ELBA | B48: USA | C48: North America | D48: Elba Island | E48: Kinder Morgan | F48: Modular T1-T10 | G48: operational | H48: 2.5 | I48: 2.5 | J48: 2016-12-07 | K48: 2020-08-15 | L48: immediate | M48: Southeast US | N48: Shell offtake | O48: KMI 10-K | P48: 2026-06-01 | Q48: 10 small modular trains of 0.25 MTPA each
A49: US-FREEPORT-T1 | B49: USA | C49: North America | D49: Freeport LNG | E49: Freeport LNG | F49: T1 | G49: operational | H49: 5.1 | I49: 5 | J49: 2014-11-17 | K49: 2019-09-03 | L49: immediate | M49: US Gulf | N49: Osaka Gas/JERA/BP/SK | O49: Freeport LNG releases | P49: 2026-06-01 | Q49: Recovered after 2022 fire
A50: US-FREEPORT-T2 | B50: USA | C50: North America | D50: Freeport LNG | E50: Freeport LNG | F50: T2 | G50: operational | H50: 5.1 | I50: 5 | J50: 2014-11-17 | K50: 2020-01-23 | L50: immediate | M50: US Gulf | N50: Same | O50: Freeport LNG | P50: 2026-06-01
A51: US-FREEPORT-T3 | B51: USA | C51: North America | D51: Freeport LNG | E51: Freeport LNG | F51: T3 | G51: operational | H51: 5.1 | I51: 5 | J51: 2014-11-17 | K51: 2020-05-19 | L51: immediate | M51: US Gulf | N51: Same | O51: Freeport LNG | P51: 2026-06-01
A52: US-SABINEPASS-T1 | B52: USA | C52: North America | D52: Sabine Pass | E52: Cheniere Energy | F52: T1 | G52: operational | H52: 4.5 | I52: 5 | J52: 2010-08-01 | K52: 2016-02-24 | L52: immediate | M52: US shale (Haynesville/Permian) | N52: BG/Shell/CFE/GAIL/GNF/KOGAS portfolio | O52: Cheniere 10-K + GIIGNL 2024 | P52: 2026-06-01 | Q52: Debottlenecked above nameplate
A53: US-SABINEPASS-T2 | B53: USA | C53: North America | D53: Sabine Pass | E53: Cheniere Energy | F53: T2 | G53: operational | H53: 4.5 | I53: 5 | J53: 2010-08-01 | K53: 2016-09-15 | L53: immediate | M53: US shale | N53: Portfolio (long-term SPAs) | O53: Cheniere 10-K | P53: 2026-06-01
A54: US-SABINEPASS-T3 | B54: USA | C54: North America | D54: Sabine Pass | E54: Cheniere Energy | F54: T3 | G54: operational | H54: 4.5 | I54: 5 | J54: 2010-08-01 | K54: 2017-03-28 | L54: immediate | M54: US shale | N54: Portfolio | O54: Cheniere 10-K | P54: 2026-06-01
A55: US-SABINEPASS-T4 | B55: USA | C55: North America | D55: Sabine Pass | E55: Cheniere Energy | F55: T4 | G55: operational | H55: 4.5 | I55: 5 | J55: 2010-08-01 | K55: 2017-10-15 | L55: immediate | M55: US shale | N55: Portfolio | O55: Cheniere 10-K | P55: 2026-06-01
A56: US-SABINEPASS-T5 | B56: USA | C56: North America | D56: Sabine Pass | E56: Cheniere Energy | F56: T5 | G56: operational | H56: 4.5 | I56: 5 | J56: 2014-06-30 | K56: 2019-03-27 | L56: immediate | M56: US shale | N56: Portfolio | O56: Cheniere 10-K | P56: 2026-06-01
A57: US-SABINEPASS-T6 | B57: USA | C57: North America | D57: Sabine Pass | E57: Cheniere Energy | F57: T6 | G57: operational | H57: 4.5 | I57: 5 | J57: 2019-06-01 | K57: 2022-02-08 | L57: immediate | M57: US shale | N57: Portfolio | O57: Cheniere 10-K | P57: 2026-06-01
A58: RU-SAKHALIN2-T1 | B58: Russia | C58: Russia/Arctic | D58: Sakhalin Energy LNG | E58: Gazprom/Mitsui/Mitsubishi | F58: T1 | G58: operational | H58: 4.8 | I58: 4.5 | J58: 2003-05-22 | K58: 2009-02-18 | L58: immediate | M58: Sakhalin shelf | N58: Japanese utilities (sanctions-exempted for now) | O58: Sakhalin Energy | P58: 2026-06-01 | Q58: Shell exited 2022
A59: RU-SAKHALIN2-T2 | B59: Russia | C59: Russia/Arctic | D59: Sakhalin Energy LNG | E59: Gazprom/Mitsui/Mitsubishi | F59: T2 | G59: operational | H59: 4.8 | I59: 4.5 | J59: 2003-05-22 | K59: 2009-06-16 | L59: immediate | M59: Same | N59: Same | O59: Same | P59: 2026-06-01
A60: RU-YAMAL-T1 | B60: Russia | C60: Russia/Arctic | D60: Yamal LNG | E60: Novatek/TotalEnergies/CNPC/Silk Road Fund | F60: T1 | G60: operational | H60: 5.5 | I60: 5 | J60: 2013-12-18 | K60: 2017-12-08 | L60: immediate | M60: South Tambey | N60: Portfolio (shadow fleet redirection post-2022) | O60: Novatek | P60: 2026-06-01
A61: RU-YAMAL-T2 | B61: Russia | C61: Russia/Arctic | D61: Yamal LNG | E61: Novatek/TotalEnergies/CNPC/Silk Road Fund | F61: T2 | G61: operational | H61: 5.5 | I61: 5 | J61: 2013-12-18 | K61: 2018-08-01 | L61: immediate | M61: Same | N61: Same | O61: Novatek | P61: 2026-06-01
A62: RU-YAMAL-T3 | B62: Russia | C62: Russia/Arctic | D62: Yamal LNG | E62: Novatek/TotalEnergies/CNPC/Silk Road Fund | F62: T3 | G62: operational | H62: 5.5 | I62: 5 | J62: 2013-12-18 | K62: 2018-12-11 | L62: immediate | M62: Same | N62: Same | O62: Novatek | P62: 2026-06-01
A63: RU-YAMAL-T4 | B63: Russia | C63: Russia/Arctic | D63: Yamal LNG | E63: Novatek | F63: T4 (Arctic Cascade) | G63: operational | H63: 0.9 | I63: 0.9 | J63: 2017-09-01 | K63: 2021-05-15 | L63: immediate | M63: South Tambey | N63: Novatek portfolio | O63: Novatek | P63: 2026-06-01 | Q63: Domestic technology pilot
A64: ID-BONTANG | B64: Indonesia | C64: SE Asia | D64: Bontang LNG | E64: Pertamina/Total/Vico/Chevron | F64: T1-T8 | G64: operational | H64: 22.5 | I64: 8 | J64: 1970-01-01 | K64: 1977-08-09 | L64: n/a | M64: East Kalimantan (declining) | N64: Legacy Japanese portfolio + domestic | O64: Pertamina | P64: 2026-06-01 | Q64: Steep production decline; effective ~8 MTPA today
A65: ID-DONGGISENORO | B65: Indonesia | C65: SE Asia | D65: Donggi-Senoro LNG | E65: Mitsubishi/Pertamina/KOGAS/Medco | F65: single | G65: operational | H65: 2 | I65: 1.9 | J65: 2011-01-21 | K65: 2015-07-23 | L65: immediate | M65: Senoro/Matindok | N65: Chubu/KOGAS | O65: DSLNG | P65: 2026-06-01
A66: ID-TANGGUH-T1 | B66: Indonesia | C66: SE Asia | D66: Tangguh LNG | E66: BP/MI Berau/CNOOC/Inpex | F66: T1 | G66: operational | H66: 3.8 | I66: 3.6 | J66: 2005-03-01 | K66: 2009-06-15 | L66: immediate | M66: Wiriagar/Vorwata | N66: Sempra Costa Azul + Korea + China | O66: BP | P66: 2026-06-01
A67: ID-TANGGUH-T2 | B67: Indonesia | C67: SE Asia | D67: Tangguh LNG | E67: BP/MI Berau/CNOOC/Inpex | F67: T2 | G67: operational | H67: 3.8 | I67: 3.6 | J67: 2005-03-01 | K67: 2009-09-15 | L67: immediate | M67: Same | N67: Same | O67: BP | P67: 2026-06-01
A68: ID-TANGGUH-T3 | B68: Indonesia | C68: SE Asia | D68: Tangguh LNG | E68: BP/MI Berau/CNOOC/Inpex | F68: T3 | G68: operational | H68: 3.8 | I68: 3.5 | J68: 2016-07-01 | K68: 2023-10-11 | L68: Y1:70%;Y2:90% | M68: Same | N68: PLN/portfolio | O68: BP | P68: 2026-06-01
A69: MY-MLNG-9 | B69: Malaysia | C69: SE Asia | D69: MLNG 9 (Train 9) | E69: Petronas | F69: T9 | G69: operational | H69: 3.6 | I69: 3.5 | J69: 2010-11-15 | K69: 2017-01-10 | L69: immediate | M69: Sarawak | N69: Portfolio | O69: Petronas | P69: 2026-06-01 | Q69: Single mega-train
A70: MY-MLNG-1 | B70: Malaysia | C70: SE Asia | D70: MLNG Bintulu Complex (legacy MLNG 1) | E70: Petronas | F70: T1-T3 | G70: operational | H70: 8.4 | I70: 7.5 | J70: 1978-01-01 | K70: 1983-12-31 | L70: immediate | M70: Sarawak | N70: Japanese long-term portfolio | O70: Petronas | P70: 2026-06-01 | Q70: Original MLNG; 3 trains
A71: MY-MLNG-2 | B71: Malaysia | C71: SE Asia | D71: MLNG Dua | E71: Petronas | F71: T4-T6 | G71: operational | H71: 9.6 | I71: 9 | J71: 1992-01-01 | K71: 1995-12-31 | L71: immediate | M71: Sarawak | N71: Same | O71: Petronas | P71: 2026-06-01 | Q71: 3 trains
A72: MY-MLNG-3 | B72: Malaysia | C72: SE Asia | D72: MLNG Tiga | E72: Petronas | F72: T7-T8 | G72: operational | H72: 7.7 | I72: 7.4 | J72: 1999-01-01 | K72: 2003-04-01 | L72: immediate | M72: Sarawak | N72: Same | O72: Petronas | P72: 2026-06-01 | Q72: 2 trains
A73: MY-PFLNG2 | B73: Malaysia | C73: SE Asia | D73: PFLNG Dua | E73: Petronas | F73: FLNG | G73: operational | H73: 1.5 | I73: 1.4 | J73: 2014-02-19 | K73: 2021-02-21 | L73: immediate | M73: Rotan field | N73: Petronas | O73: Petronas | P73: 2026-06-01
A74: MY-PFLNG1 | B74: Malaysia | C74: SE Asia | D74: PFLNG Satu | E74: Petronas | F74: FLNG | G74: operational | H74: 1.2 | I74: 1.1 | J74: 2012-06-21 | K74: 2017-04-17 | L74: immediate | M74: Kanowit field | N74: Petronas | O74: Petronas | P74: 2026-06-01 | Q74: World's first FLNG
A75: MR-SN-TORTUE | B75: Mauritania | C75: Sub-Saharan Africa | D75: Tortue Ahmeyim FLNG Phase 1 | E75: BP/Kosmos/SMHPM/PETROSEN | F75: FLNG | G75: operational | H75: 2.7 | I75: 2.4 | J75: 2018-12-21 | K75: 2025-02-15 | L75: Y1:60%;Y2:90%;Y3:100% | M75: GTA field shared MR/SN | N75: BP offtake | O75: BP press release Feb 2025; kosmosenergy.com; offshore-technology.com | P75: 2026-06-22 | Q75: Nameplate corrected to 2.7 MTPA per Kosmos/Golar disclosures; ramped to ~90% (~2.4 MTPA) by mid-2025; COD confirmed by Kosmos per offshore-technology.com
A76: MZ-CORALSUL | B76: Mozambique | C76: Sub-Saharan Africa | D76: Coral Sul FLNG | E76: Eni/ExxonMobil/CNPC/Galp/KOGAS/ENH | F76: FLNG | G76: operational | H76: 3.4 | I76: 3.4 | J76: 2017-06-01 | K76: 2022-11-13 | L76: Y1:80%;Y2:100% | M76: Coral South gas field | N76: BP offtake long-term | O76: Eni | P76: 2026-06-01 | Q76: Ramped successfully despite security risks onshore
A77: NG-NLNG-T1-T2 | B77: Nigeria | C77: Sub-Saharan Africa | D77: Nigeria LNG | E77: NNPC/Shell/TotalEnergies/Eni | F77: T1-T2 | G77: operational | H77: 6.5 | I77: 6 | J77: 1995-01-01 | K77: 1999-10-09 | L77: immediate | M77: Niger Delta | N77: Long-term portfolio | O77: NLNG | P77: 2026-06-01 | Q77: Bonny Island
A78: NG-NLNG-T3 | B78: Nigeria | C78: Sub-Saharan Africa | D78: Nigeria LNG | E78: NNPC/Shell/TotalEnergies/Eni | F78: T3 | G78: operational | H78: 3 | I78: 2.8 | J78: 1999-01-01 | K78: 2002-11-01 | L78: immediate | M78: Niger Delta | N78: Same | O78: NLNG | P78: 2026-06-01
A79: NG-NLNG-T4-T5 | B79: Nigeria | C79: Sub-Saharan Africa | D79: Nigeria LNG | E79: NNPC/Shell/TotalEnergies/Eni | F79: T4-T5 | G79: operational | H79: 8.4 | I79: 7.8 | J79: 2002-01-01 | K79: 2005-11-01 | L79: immediate | M79: Niger Delta | N79: Same | O79: NLNG | P79: 2026-06-01 | Q79: Mid-2000s expansion
A80: NG-NLNG-T6 | B80: Nigeria | C80: Sub-Saharan Africa | D80: Nigeria LNG | E80: NNPC/Shell/TotalEnergies/Eni | F80: T6 | G80: operational | H80: 4.1 | I80: 3.8 | J80: 2004-01-01 | K80: 2007-12-01 | L80: immediate | M80: Niger Delta | N80: Same | O80: NLNG | P80: 2026-06-01 | Q80: Feedgas curtailed by upstream security

Sheet Liquefaction — Upcoming
A1: Facility ID | B1: Country | C1: Region | D1: Facility | E1: Operator | F1: Train | G1: Status | H1: Nameplate (MTPA) | I1: Effective (MTPA) | J1: FID | K1: Start / COD | L1: Ramp-up | M1: Feedgas | N1: Offtake | O1: Source | P1: Updated | Q1: Notes
A2: RU-ARCTIC2-T2 | B2: Russia | C2: Russia/Arctic | D2: Arctic LNG-2 | E2: Novatek | F2: T2 | G2: paused | H2: 6.6 | I2: 0 | J2: 2019-09-05 | L2: deferred | M2: Utrennoye | N2: None | O2: Argus | P2: 2026-06-01 | Q2: Sanctioned; tow to site delayed
A3: RU-ARCTIC2-T3 | B3: Russia | C3: Russia/Arctic | D3: Arctic LNG-2 | E3: Novatek | F3: T3 | G3: paused | H3: 6.6 | I3: 0 | J3: 2019-09-05 | L3: deferred | M3: Utrennoye | N3: None | O3: Argus | P3: 2026-06-01 | Q3: T3 construction halted
A4: TT-ATLANTIC-T1 | B4: Trinidad and Tobago | C4: Latin America | D4: Atlantic LNG | E4: Shell/BP/NGC/CIC | F4: T1 | G4: mothballed | H4: 3.3 | I4: 0 | J4: 1995-01-01 | K4: 1999-04-16 | L4: n/a | M4: Trinidad | N4: Legacy portfolio | O4: Atlantic LNG | P4: 2026-06-01 | Q4: Mothballed amid feedgas decline
A5: RU-ARCTIC2-T1 | B5: Russia | C5: Russia/Arctic | D5: Arctic LNG-2 | E5: Novatek/CNPC/CNOOC/Mitsui/JOGMEC | F5: T1 | G5: paused | H5: 6.6 | I5: 1.3 | J5: 2019-09-05 | K5: 2024-01-15 | L5: severely constrained | M5: Utrennoye field | N5: No formal offtake post-sanctions; Beihai terminal China sole buyer | O5: Reuters/Argus/Platts LNG Daily; bairdmaritime.com 2026-01; energyconnects.com Nov 2025; gcaptain.com Aug 2025 | P5: 2026-06-22 | Q5: Mothballed Oct 2024-Mar 2025 after loading ~10 unsold cargoes; deliveries to China (Beihai) began Aug 2025; 23 cargoes/1.3 Mt delivered to China in full-year 2025; first 2026 cargo discharged Jan 26 2026; output constrained by lack of Arc7 tankers; ~1.3 MTPA realized vs 6.6 MTPA nameplate; TotalEnergies exit approved by Putin Jun 2026
A6: US-PLAQUEMINES-P1 | B6: USA | C6: North America | D6: Plaquemines LNG Phase 1 | E6: Venture Global LNG | F6: Modular T1-T18 (Ph1) | G6: commissioning | H6: 10 | I6: 10 | J6: 2022-05-25 | K6: 2024-12-26 | L6: Y1:60%;Y2:90%;Y3:100% | M6: US Gulf | N6: Shell/BP/PGNiG/EDF/CPC/Sinopec/ExxonMobil | O6: VG press release Dec 2024 | P6: 2026-06-01 | Q6: Phase 1 commissioning; ramp through 2026
A7: US-GOLDENPASS-T1 | B7: USA | C7: North America | D7: Golden Pass LNG | E7: QatarEnergy/ExxonMobil | F7: T1 | G7: commissioning | H7: 5.2 | I7: 5.2 | J7: 2019-02-05 | K7: 2026-03-30 | L7: Y1:60%;Y2:90%;Y3:100% | M7: Pipeline gas | N7: QatarEnergy/ExxonMobil offtake | O7: Operator releases + EIA; EIA eia.gov/todayinenergy id=67564; energyconnects.com Apr 2026 | P7: 2026-06-22 | Q7: First LNG 2026-03-30; first cargo shipped 2026-04-22; T1 in commissioning ramp; commercial ops declaration pending
A8: QA-QATARENERGY-NFE-T1 | B8: Qatar | C8: MENA | D8: North Field East | E8: QatarEnergy/Shell/TotalEnergies/ExxonMobil/ConocoPhillips/Eni | F8: T1 | G8: commissioning | H8: 8 | I8: 8 | J8: 2022-02-21 | K8: 2026-07-01 | L8: Y1:60%;Y2:90%;Y3:100% | M8: North Field | N8: Sinopec/CNPC/Shell/TotalEnergies/ExxonMobil long-term SPAs | O8: QatarEnergy/IEA; lngindustry.com May 2025; mees.com Dec 2025; themiddleeastinsider.com Apr 2026 | P8: 2026-06-22 | Q8: First LNG Nov 2025; pre-commissioning progressing; QatarEnergy targeting COD Q3 2026; slipped from Q1 2026 original target
A9: US-COSTAAZUL-T1 | B9: Mexico | C9: North America | D9: Energía Costa Azul | E9: Sempra Infrastructure | F9: T1 | G9: commissioning | H9: 3.25 | I9: 3.25 | J9: 2020-11-17 | K9: 2026-09-30 | L9: Y1:80%;Y2:100% | M9: US Permian via piped gas | N9: Mitsui/TotalEnergies portfolio | O9: Sempra Q4 2024; woodmac.com May 2026; naturalgasintel.com May 2026 | P9: 2026-06-22 | Q9: Flaring detected May 24 2026 confirming early commissioning; gas intake ramping from Apr 2026; first cargo timeline stretched to Q3 2026 per Wood Mackenzie
A10: AU-PLUTO-T2 | B10: Australia | C10: Australia | D10: Pluto LNG | E10: Woodside | F10: T2 | G10: construction | H10: 5 | I10: 5 | J10: 2021-11-22 | K10: 2026-12-31 | L10: Y1:60%;Y2:90%;Y3:100% | M10: Scarborough field | N10: Portfolio | O10: Woodside; woodside.com 6-K FY2026; chemanalyst.com; offshore-technology.com | P10: 2026-06-22 | Q10: Scarborough-fed; 96%+ complete (ex-T1 mods); all 51 modules at site; targeting Q4 2026 first LNG cargo; COD slipped modestly from 2026-09-30
A11: US-CORPUSCHRISTI-CC3 | B11: USA | C11: North America | D11: Corpus Christi Stage 3 | E11: Cheniere Energy | F11: Midscale T1-T7 | G11: commissioning | H11: 10.4 | I11: 10 | J11: 2022-06-22 | K11: 2026-12-31 | L11: Y1:60%;Y2:90%;Y3:100% | M11: US shale | N11: Portfolio + JERA Equinor TotalEnergies | O11: Cheniere press release Dec 2024; lngprime.com CC3 96.5% complete; naturalgasintel.com May 2026 | P11: 2026-06-22 | Q11: 6 of 7 midscale trains producing LNG as of May 2026; T7 on track for fall 2026; full seven-train completion expected end-2026
A12: US-GOLDENPASS-T2 | B12: USA | C12: North America | D12: Golden Pass LNG | E12: QatarEnergy/ExxonMobil | F12: T2 | G12: construction | H12: 5.2 | I12: 5.2 | J12: 2019-02-05 | K12: 2026-12-31 | L12: Y1:60%;Y2:90%;Y3:100% | M12: Pipeline gas | N12: Same | O12: Operator releases; naturalgasintel.com ExxonMobil Q1 2026 earnings | P12: 2026-06-22 | Q12: Mechanical completion expected end-2026; COD Q4 2026 per ExxonMobil Q1 2026 earnings call
A13: NG-NLNG-T7 | B13: Nigeria | C13: Sub-Saharan Africa | D13: Nigeria LNG | E13: NNPC/Shell/TotalEnergies/Eni | F13: T7 | G13: construction | H13: 8 | I13: 7.5 | J13: 2019-12-20 | K13: 2026-12-31 | L13: Y1:60%;Y2:90%;Y3:100% | M13: Niger Delta | N13: Portfolio | O13: NLNG | P13: 2026-06-01 | Q13: Expansion train
A14: US-GOLDENPASS-T3 | B14: USA | C14: North America | D14: Golden Pass LNG | E14: QatarEnergy/ExxonMobil | F14: T3 | G14: construction | H14: 5.2 | I14: 5.2 | J14: 2019-02-05 | K14: 2027-03-31 | L14: Y1:60%;Y2:90%;Y3:100% | M14: Pipeline gas | N14: Same | O14: Operator releases; naturalgasintel.com ExxonMobil Q1 2026 | P14: 2026-06-22 | Q14: T3 now targeted Q1 2027 per ExxonMobil Q1 2026 earnings; pulled in from 2027-12-31
A15: QA-QATARENERGY-NFE-T2 | B15: Qatar | C15: MENA | D15: North Field East | E15: QatarEnergy/Shell/TotalEnergies/ExxonMobil/ConocoPhillips/Eni | F15: T2 | G15: construction | H15: 8 | I15: 8 | J15: 2022-02-21 | K15: 2027-04-30 | L15: Y1:60%;Y2:90%;Y3:100% | M15: North Field | N15: Same | O15: QatarEnergy | P15: 2026-06-01
A16: US-PLAQUEMINES-P2 | B16: USA | C16: North America | D16: Plaquemines LNG Phase 2 | E16: Venture Global LNG | F16: Modular Ph2 | G16: construction | H16: 10 | I16: 10 | J16: 2023-03-29 | K16: 2027-06-30 | L16: Y1:60%;Y2:90%;Y3:100% | M16: US Gulf | N16: Same portfolio | O16: VG releases 2024; FERC extension request to 2027-12-31 filed Sep 2025; naturalgasintel.com | P16: 2026-06-22 | Q16: VG sought FERC extension to Dec 2027; Phase 2 now targeting mid-2027 in-service; Phase 1 expected commercial ops Q4 2026
A17: QA-QATARENERGY-NFE-T3 | B17: Qatar | C17: MENA | D17: North Field East | E17: QatarEnergy/Shell/TotalEnergies/ExxonMobil/ConocoPhillips/Eni | F17: T3 | G17: construction | H17: 8 | I17: 8 | J17: 2022-02-21 | K17: 2027-09-30 | L17: Y1:60%;Y2:90%;Y3:100% | M17: North Field | N17: Same | O17: QatarEnergy | P17: 2026-06-01
A18: US-PORTARTHUR-T1 | B18: USA | C18: North America | D18: Port Arthur LNG Phase 1 | E18: Sempra Infrastructure | F18: T1 | G18: construction | H18: 6.5 | I18: 6.5 | J18: 2023-03-20 | K18: 2027-09-30 | L18: Y1:60%;Y2:90%;Y3:100% | M18: US Gulf | N18: KOGAS/ConocoPhillips/RWE/PKN Orlen/INEOS | O18: Sempra press releases | P18: 2026-06-01
A19: US-RIOGRANDE-T1 | B19: USA | C19: North America | D19: Rio Grande LNG | E19: NextDecade | F19: T1 | G19: construction | H19: 5.4 | I19: 5.4 | J19: 2023-07-12 | K19: 2027-09-30 | L19: Y1:50%;Y2:80%;Y3:100% | M19: Permian | N19: TotalEnergies/Shell/ENN/Galp/Itochu/Guangdong portfolio | O19: NextDecade press release | P19: 2026-06-01 | Q19: Phase 1 FID July 2023
A20: QA-QATARENERGY-NFE-T4 | B20: Qatar | C20: MENA | D20: North Field East | E20: QatarEnergy/Shell/TotalEnergies/ExxonMobil/ConocoPhillips/Eni | F20: T4 | G20: construction | H20: 8 | I20: 8 | J20: 2022-02-21 | K20: 2027-12-31 | L20: Y1:60%;Y2:90%;Y3:100% | M20: North Field | N20: Same | O20: QatarEnergy | P20: 2026-06-01
A21: CA-WOODFIBRE | B21: Canada | C21: North America | D21: Woodfibre LNG | E21: Pacific Energy/Enbridge | F21: single | G21: construction | H21: 2.1 | I21: 2.1 | J21: 2023-09-15 | K21: 2027-12-31 | L21: immediate | M21: Montney via pipeline | N21: BP offtake | O21: Woodfibre Press | P21: 2026-06-01 | Q21: Squamish BC
A22: US-PORTARTHUR-T2 | B22: USA | C22: North America | D22: Port Arthur LNG Phase 1 | E22: Sempra Infrastructure | F22: T2 | G22: construction | H22: 6.5 | I22: 6.5 | J22: 2023-03-20 | K22: 2028-03-31 | L22: Y1:60%;Y2:90%;Y3:100% | M22: US Gulf | N22: Same | O22: Sempra | P22: 2026-06-01
A23: US-RIOGRANDE-T2 | B23: USA | C23: North America | D23: Rio Grande LNG | E23: NextDecade | F23: T2 | G23: construction | H23: 5.4 | I23: 5.4 | J23: 2023-07-12 | K23: 2028-03-31 | L23: Y1:50%;Y2:80%;Y3:100% | M23: Permian | N23: Same | O23: NextDecade | P23: 2026-06-01
A24: MX-SAGUARO-T1 | B24: Mexico | C24: North America | D24: Saguaro Energía LNG | E24: Mexico Pacific | F24: T1 | G24: construction | H24: 5 | I24: 5 | J24: 2024-09-04 | K24: 2028-06-30 | L24: Y1:50%;Y2:80%;Y3:100% | M24: Permian via pipeline | N24: Shell/Woodside/ConocoPhillips/Zhejiang | O24: MPL press release | P24: 2026-06-01 | Q24: FID achieved 2024; Sonora coast
A25: QA-QATARENERGY-NFS-T1 | B25: Qatar | C25: MENA | D25: North Field South | E25: QatarEnergy/Shell/TotalEnergies/ConocoPhillips | F25: T1 | G25: construction | H25: 8 | I25: 8 | J25: 2023-10-23 | K25: 2028-12-31 | L25: Y1:60%;Y2:90%;Y3:100% | M25: North Field | N25: Same JV partners; portfolio | O25: QatarEnergy | P25: 2026-06-01 | Q25: NFS Phase 2 of expansion
A26: CA-CEDAR | B26: Canada | C26: North America | D26: Cedar LNG | E26: Pembina Pipeline/Haisla Nation | F26: FLNG | G26: construction | H26: 3.3 | I26: 3.3 | J26: 2024-06-25 | K26: 2028-12-31 | L26: immediate | M26: Western Canadian | N26: ARC Energy/Pembina offtake | O26: Pembina 2024 FID | P26: 2026-06-01 | Q26: FLNG Kitimat
A27: US-RIOGRANDE-T3 | B27: USA | C27: North America | D27: Rio Grande LNG | E27: NextDecade | F27: T3 | G27: construction | H27: 5.4 | I27: 5.4 | J27: 2024-06-21 | K27: 2028-12-31 | L27: Y1:50%;Y2:80%;Y3:100% | M27: Permian | N27: Same | O27: NextDecade 2024 FID | P27: 2026-06-01 | Q27: T3 FID 2024
A28: QA-QATARENERGY-NFS-T2 | B28: Qatar | C28: MENA | D28: North Field South | E28: QatarEnergy/Shell/TotalEnergies/ConocoPhillips | F28: T2 | G28: construction | H28: 8 | I28: 8 | J28: 2023-10-23 | K28: 2029-06-30 | L28: Y1:60%;Y2:90%;Y3:100% | M28: North Field | N28: Same | O28: QatarEnergy | P28: 2026-06-01
A29: MZ-MOZAMBIQUE-LNG-T1 | B29: Mozambique | C29: Sub-Saharan Africa | D29: Mozambique LNG | E29: TotalEnergies/Mitsui/Bharat/ONGC/PTTEP | F29: T1 | G29: construction | H29: 6.44 | I29: 0 | J29: 2019-06-18 | K29: 2029-12-31 | L29: deferred | M29: Area 1 (Golfinho-Atum) | N29: Asian utility portfolio | O29: TotalEnergies; totalenergies.com Jan 2026 press release; aljazeera.com 2026-01-29 | P29: 2026-06-22 | Q29: FM lifted Nov 7 2025; full restart announced Jan 29 2026; construction restarted; 40% progress; first LNG now targeted 2029; 4000+ workers mobilised
A30: MZ-MOZAMBIQUE-LNG-T2 | B30: Mozambique | C30: Sub-Saharan Africa | D30: Mozambique LNG | E30: TotalEnergies/Mitsui/Bharat/ONGC/PTTEP | F30: T2 | G30: construction | H30: 6.44 | I30: 0 | J30: 2019-06-18 | K30: 2030-06-30 | L30: deferred | M30: Area 1 | N30: Same | O30: TotalEnergies; totalenergies.com Jan 2026 | P30: 2026-06-22 | Q30: FM lifted with T1; T2 restart concurrent; first LNG 2029-2030 range
A31: MZ-ROVUMA-T1 | B31: Mozambique | C31: Sub-Saharan Africa | D31: Rovuma LNG | E31: ExxonMobil(op)/Eni/CNPC(MRV 70%); ENH 10%; ADNOC/XRG 10%; KOGAS 10% | F31: T1 | G31: planned | H31: 9 | I31: 0 | K31: 2030-12-31 | L31: Y1:50%;Y2:80%;Y3:100% | M31: Area 4 Rovuma Basin offshore (Mamba complex) | N31: No signed offtake; LOIs reported with Asian utilities | O31: ExxonMobil corporate.exxonmobil.com/locations/mozambique/rovuma-lng; Technip Energies/JGC FEED award jgc.com Sep 2024; 360mozambique.com Jun 2026; offshore-energy.biz; furtherafrica.com Nov 2025 | P31: 2026-06-22 | Q31: FID targeted H2 2026 per Mozambique govt and ExxonMobil; not yet confirmed as of 2026-06-22; FM lifted Nov 20 2025; FEED (Technip Energies + JGC) awarded Sep 2024 ~16-month duration; revised development plan filed Apr 2026 featuring 12 modular electric-driven trains of 1.5 MTPA (grouped as 2 x 9 MTPA processing trains here); start_date is 2030 target — high uncertainty flagged; ADNOC/XRG replaced Galp (completed Mar 2025 for $881M); project cost ~$30B
A32: MZ-ROVUMA-T2 | B32: Mozambique | C32: Sub-Saharan Africa | D32: Rovuma LNG | E32: ExxonMobil(op)/Eni/CNPC(MRV 70%); ENH 10%; ADNOC/XRG 10%; KOGAS 10% | F32: T2 | G32: planned | H32: 9 | I32: 0 | K32: 2031-12-31 | L32: Y1:50%;Y2:80%;Y3:100% | M32: Area 4 Rovuma Basin offshore (Mamba complex) | N32: No signed offtake; LOIs reported with Asian utilities | O32: ExxonMobil corporate.exxonmobil.com/locations/mozambique/rovuma-lng; 360mozambique.com Jun 2026; offshore-energy.biz; furtherafrica.com Nov 2025 | P32: 2026-06-22 | Q32: Second train group; start_date 2031 is speculative extrapolation from 2030 T1 target — no operator public guidance for T2 separately; contingent on T1 ramp and FID confirmation

Sheet Regasification — Operational
A1: Facility ID | B1: Country | C1: Region | D1: Facility | E1: Operator | F1: Type | G1: Status | H1: Send-out (Bcm/y) | I1: Send-out (MTPA) | J1: Storage (m³ LNG) | K1: Start | L1: Reload? | M1: Source | N1: Updated | O1: Notes
A2: CN-CAOFEIDIAN | B2: China | C2: East Asia | D2: Caofeidian | E2: PetroChina | F2: onshore | G2: operational | H2: 10 | I2: 7.4 | J2: 720000 | K2: 2013-11-23 | L2: yes | M2: PetroChina | N2: 2026-06-01
A3: CN-DAPENG | B3: China | C3: East Asia | D3: Dapeng (Shenzhen) | E3: CNOOC | F3: onshore | G3: operational | H3: 9.4 | I3: 6.9 | J3: 640000 | K3: 2006-06-26 | L3: yes | M3: CNOOC | N3: 2026-06-01 | O3: First mainland China LNG terminal
A4: CN-PUTIAN | B4: China | C4: East Asia | D4: Putian (Fujian) | E4: CNOOC | F4: onshore | G4: operational | H4: 7.2 | I4: 5.3 | J4: 640000 | K4: 2008-05-01 | L4: yes | M4: CNOOC | N4: 2026-06-01
A5: CN-QINGDAO | B5: China | C5: East Asia | D5: Qingdao | E5: Sinopec | F5: onshore | G5: operational | H5: 6 | I5: 4.4 | J5: 640000 | K5: 2014-11-15 | L5: yes | M5: Sinopec | N5: 2026-06-01
A6: CN-TANGSHAN | B6: China | C6: East Asia | D6: Tangshan | E6: PetroChina | F6: onshore | G6: operational | H6: 10 | I6: 7.4 | J6: 800000 | K6: 2014-11-04 | L6: yes | M6: PetroChina | N6: 2026-06-01
A7: CN-TIANJIN | B7: China | C7: East Asia | D7: Tianjin Nangang | E7: Sinopec | F7: onshore | G7: operational | H7: 12 | I7: 8.8 | J7: 640000 | K7: 2013-11-15 | L7: yes | M7: Sinopec | N7: 2026-06-01 | O7: Strategic location for north China
A8: CN-YANGSHAN | B8: China | C8: East Asia | D8: Yangshan Shanghai | E8: CNOOC/Shenergy | F8: onshore | G8: operational | H8: 9 | I8: 6.6 | J8: 495000 | K8: 2009-10-01 | L8: yes | M8: CNOOC | N8: 2026-06-01
A9: JP-CHITA | B9: Japan | C9: East Asia | D9: Chita Joint Works | E9: Toho Gas/Chubu Electric | F9: onshore | G9: operational | H9: 9.5 | I9: 7 | J9: 1620000 | K9: 1977-12-01 | L9: yes | M9: Toho Gas | N9: 2026-06-01 | O9: Multi-operator complex
A10: JP-FUTTSU | B10: Japan | C10: East Asia | D10: Futtsu | E10: TEPCO/Chubu | F10: onshore | G10: operational | H10: 30 | I10: 22 | J10: 1110000 | K10: 1985-04-01 | L10: yes | M10: Japan METI | N10: 2026-06-01 | O10: Largest single LNG terminal globally
A11: JP-HIGASHIOHGISHIMA | B11: Japan | C11: East Asia | D11: Higashi-Ohgishima | E11: TEPCO | F11: onshore | G11: operational | H11: 12.5 | I11: 9.2 | J11: 540000 | K11: 1984-08-01 | L11: yes | M11: METI | N11: 2026-06-01
A12: JP-NEGISHI | B12: Japan | C12: East Asia | D12: Negishi | E12: Tokyo Gas/TEPCO | F12: onshore | G12: operational | H12: 10 | I12: 7.4 | J12: 2370000 | K12: 1969-10-01 | L12: yes | M12: Tokyo Gas | N12: 2026-06-01 | O12: Oldest commercial LNG terminal in Japan
A13: JP-OHGISHIMA | B13: Japan | C13: East Asia | D13: Ohgishima | E13: TEPCO | F13: onshore | G13: operational | H13: 12.5 | I13: 9.2 | J13: 540000 | K13: 1998-04-01 | L13: yes | M13: METI | N13: 2026-06-01
A14: JP-SENBOKU2 | B14: Japan | C14: East Asia | D14: Senboku II | E14: Osaka Gas | F14: onshore | G14: operational | H14: 10 | I14: 7.4 | J14: 1820000 | K14: 1972-04-01 | L14: yes | M14: Osaka Gas | N14: 2026-06-01
A15: JP-SODEGAURA | B15: Japan | C15: East Asia | D15: Sodegaura | E15: Tokyo Gas | F15: onshore | G15: operational | H15: 17.6 | I15: 13 | J15: 2660000 | K15: 1973-09-01 | L15: yes | M15: Tokyo Gas | N15: 2026-06-01
A16: JP-YOKKAICHI | B16: Japan | C16: East Asia | D16: Yokkaichi | E16: Chubu Electric | F16: onshore | G16: operational | H16: 10 | I16: 7.4 | J16: 640000 | K16: 1988-02-01 | L16: yes | M16: Chubu | N16: 2026-06-01
A17: KR-BORYEONG | B17: South Korea | C17: East Asia | D17: Boryeong | E17: SK E&S/GS Energy | F17: onshore | G17: operational | H17: 4.8 | I17: 3.5 | J17: 400000 | K17: 2017-01-01 | L17: yes | M17: SK E&S | N17: 2026-06-01 | O17: Private; supplies SK power plants
A18: KR-GWANGYANG | B18: South Korea | C18: East Asia | D18: Gwangyang | E18: POSCO | F18: onshore | G18: operational | H18: 5.4 | I18: 4 | J18: 530000 | K18: 2005-10-01 | L18: no | M18: POSCO | N18: 2026-06-01
A19: KR-INCHEON | B19: South Korea | C19: East Asia | D19: Incheon | E19: KOGAS | F19: onshore | G19: operational | H19: 36 | I19: 26.5 | J19: 3360000 | K19: 1996-10-01 | L19: yes | M19: KOGAS | N19: 2026-06-01
A20: KR-PYEONGTAEK | B20: South Korea | C20: East Asia | D20: Pyeongtaek | E20: KOGAS | F20: onshore | G20: operational | H20: 42 | I20: 30.9 | J20: 3360000 | K20: 1986-11-01 | L20: yes | M20: KOGAS | N20: 2026-06-01 | O20: KOGAS' largest
A21: KR-SAMCHEOK | B21: South Korea | C21: East Asia | D21: Samcheok | E21: KOGAS | F21: onshore | G21: operational | H21: 18 | I21: 13.2 | J21: 1660000 | K21: 2014-07-01 | L21: yes | M21: KOGAS | N21: 2026-06-01
A22: KR-TONGYEONG | B22: South Korea | C22: East Asia | D22: Tongyeong | E22: KOGAS | F22: onshore | G22: operational | H22: 29.8 | I22: 21.9 | J22: 2160000 | K22: 2002-06-01 | L22: yes | M22: KOGAS | N22: 2026-06-01
A23: TW-TAICHUNG | B23: Taiwan | C23: East Asia | D23: Taichung | E23: CPC Corporation | F23: onshore | G23: operational | H23: 13.5 | I23: 9.9 | J23: 720000 | K23: 2009-03-01 | L23: yes | M23: CPC | N23: 2026-06-01
A24: TW-YUNGAN | B24: Taiwan | C24: East Asia | D24: Yung-An | E24: CPC Corporation | F24: onshore | G24: operational | H24: 10.5 | I24: 7.7 | J24: 690000 | K24: 1990-03-01 | L24: yes | M24: CPC | N24: 2026-06-01
A25: BE-ZEEBRUGGE | B25: Belgium | C25: Europe | D25: Zeebrugge | E25: Fluxys | F25: onshore | G25: operational | H25: 9 | I25: 6.6 | J25: 380000 | K25: 1987-03-01 | L25: yes | M25: Fluxys | N25: 2026-06-01
A26: HR-KRK | B26: Croatia | C26: Europe | D26: LNG Croatia (Krk) | E26: LNG Hrvatska | F26: FSRU | G26: operational | H26: 6.1 | I26: 4.5 | J26: 140000 | K26: 2021-01-01 | L26: no | M26: LNG Hrvatska | N26: 2026-06-01 | O26: Expanding to 8.4 BCm/y
A27: FR-DUNKIRK | B27: France | C27: Europe | D27: Dunkirk LNG | E27: Dunkerque LNG (Fluxys/Total) | F27: onshore | G27: operational | H27: 13 | I27: 9.6 | J27: 570000 | K27: 2017-01-01 | L27: yes | M27: Dunkerque LNG | N27: 2026-06-01
A28: FR-FOSCAVAOU | B28: France | C28: Europe | D28: Fos Cavaou | E28: Elengy/TotalEnergies | F28: onshore | G28: operational | H28: 8.3 | I28: 6.1 | J28: 330000 | K28: 2010-03-01 | L28: yes | M28: Elengy | N28: 2026-06-01
A29: FR-FOSTONKIN | B29: France | C29: Europe | D29: Fos Tonkin | E29: Elengy | F29: onshore | G29: operational | H29: 3 | I29: 2.2 | J29: 80000 | K29: 1972-06-01 | L29: no | M29: Elengy | N29: 2026-06-01
A30: FR-MONTOIR | B30: France | C30: Europe | D30: Montoir-de-Bretagne | E30: Elengy | F30: onshore | G30: operational | H30: 10 | I30: 7.4 | J30: 360000 | K30: 1980-03-01 | L30: yes | M30: Elengy | N30: 2026-06-01
A31: DE-BRUNSBUTTEL-FSRU | B31: Germany | C31: Europe | D31: Brunsbüttel FSRU | E31: DET/RWE | F31: FSRU | G31: operational | H31: 3.5 | I31: 2.6 | J31: 170000 | K31: 2023-01-20 | L31: no | M31: DET | N31: 2026-06-01
A32: DE-MUKRAN-FSRU | B32: Germany | C32: Europe | D32: Mukran FSRU | E32: DET/Deutsche ReGas | F32: FSRU | G32: operational | H32: 5.2 | I32: 3.8 | J32: 340000 | K32: 2024-03-15 | L32: no | M32: DET | N32: 2026-06-01 | O32: 2 FSRUs at Rügen
A33: DE-WILHELMSHAVEN-FSRU | B33: Germany | C33: Europe | D33: Wilhelmshaven 1 FSRU | E33: DET/Uniper | F33: FSRU | G33: operational | H33: 7.5 | I33: 5.5 | J33: 170000 | K33: 2022-12-21 | L33: no | M33: Uniper/DET | N33: 2026-06-01 | O33: Germany's first LNG terminal
A34: GR-ALEXANDROUPOLIS | B34: Greece | C34: Europe | D34: Alexandroupolis FSRU | E34: Gastrade | F34: FSRU | G34: operational | H34: 5.5 | I34: 4 | J34: 170000 | K34: 2024-10-01 | L34: no | M34: Gastrade | N34: 2026-06-01 | O34: Strategic for Balkans
A35: GR-REVITHOUSSA | B35: Greece | C35: Europe | D35: Revithoussa | E35: DESFA | F35: onshore | G35: operational | H35: 7 | I35: 5.1 | J35: 225000 | K35: 2000-02-01 | L35: yes | M35: DESFA | N35: 2026-06-01
A36: IT-ROVIGO | B36: Italy | C36: Europe | D36: Adriatic LNG (Rovigo) | E36: ExxonMobil/QatarEnergy/Snam | F36: onshore | G36: operational | H36: 9 | I36: 6.6 | J36: 250000 | K36: 2009-10-01 | L36: yes | M36: Adriatic LNG | N36: 2026-06-01 | O36: Offshore GBS
A37: IT-PANIGAGLIA | B37: Italy | C37: Europe | D37: Panigaglia | E37: Snam | F37: onshore | G37: operational | H37: 3.4 | I37: 2.5 | J37: 100000 | K37: 1971-01-01 | L37: no | M37: Snam | N37: 2026-06-01
A38: IT-PIOMBINO-FSRU | B38: Italy | C38: Europe | D38: Piombino FSRU (Italis LNG) | E38: Snam | F38: FSRU | G38: operational | H38: 5 | I38: 3.7 | J38: 170000 | K38: 2023-05-17 | L38: no | M38: Snam | N38: 2026-06-01 | O38: Will relocate to Ravenna 2026
A39: LT-KLAIPEDA | B39: Lithuania | C39: Europe | D39: Klaipėda FSRU (Independence) | E39: KN Energies | F39: FSRU | G39: operational | H39: 4 | I39: 2.9 | J39: 170000 | K39: 2014-10-27 | L39: no | M39: KN Energies | N39: 2026-06-01 | O39: Baltic strategic terminal
A40: NL-EEMSHAVEN-FSRU | B40: Netherlands | C40: Europe | D40: Eemshaven LNG (EemsEnergy) | E40: Gasunie/Vopak | F40: FSRU | G40: operational | H40: 8 | I40: 5.9 | J40: 170000 | K40: 2022-09-15 | L40: yes | M40: Gasunie | N40: 2026-06-01 | O40: 2 FSRUs; built in 6 months in response to 2022 crisis
A41: NL-GATE | B41: Netherlands | C41: Europe | D41: Gate Rotterdam | E41: Vopak/Gasunie | F41: onshore | G41: operational | H41: 16 | I41: 11.8 | J41: 540000 | K41: 2011-09-01 | L41: yes | M41: Gate Terminal | N41: 2026-06-01 | O41: Expansion to 20+ bcm/y in progress
A42: PL-SWINOUJSCIE | B42: Poland | C42: Europe | D42: Świnoujście | E42: Gaz-System | F42: onshore | G42: operational | H42: 8.3 | I42: 6.1 | J42: 320000 | K42: 2015-12-12 | L42: yes | M42: Gaz-System | N42: 2026-06-01 | O42: Expansion to ~10 BCm/y
A43: ES-BARCELONA | B43: Spain | C43: Europe | D43: Barcelona | E43: Enagás | F43: onshore | G43: operational | H43: 17.1 | I43: 12.6 | J43: 840000 | K43: 1969-03-01 | L43: yes | M43: Enagás | N43: 2026-06-01 | O43: Europe's oldest
A44: ES-BILBAO | B44: Spain | C44: Europe | D44: Bilbao (Bahía de Bizkaia) | E44: BBG | F44: onshore | G44: operational | H44: 7 | I44: 5.1 | J44: 300000 | K44: 2003-08-01 | L44: yes | M44: BBG | N44: 2026-06-01
A45: ES-CARTAGENA | B45: Spain | C45: Europe | D45: Cartagena | E45: Enagás | F45: onshore | G45: operational | H45: 11.8 | I45: 8.7 | J45: 587000 | K45: 1989-01-01 | L45: yes | M45: Enagás | N45: 2026-06-01
A46: ES-ELMUSEL | B46: Spain | C46: Europe | D46: El Musel | E46: Enagás | F46: onshore | G46: operational | H46: 8 | I46: 5.9 | J46: 300000 | K46: 2023-03-30 | L46: yes | M46: Enagás | N46: 2026-06-01 | O46: Activated 2023 after years dormant; storage hub
A47: ES-HUELVA | B47: Spain | C47: Europe | D47: Huelva | E47: Enagás | F47: onshore | G47: operational | H47: 11.8 | I47: 8.7 | J47: 610000 | K47: 1988-08-01 | L47: yes | M47: Enagás | N47: 2026-06-01
A48: ES-MUGARDOS | B48: Spain | C48: Europe | D48: Mugardos | E48: Reganosa | F48: onshore | G48: operational | H48: 3.6 | I48: 2.6 | J48: 300000 | K48: 2007-06-01 | L48: yes | M48: Reganosa | N48: 2026-06-01 | O48: Galicia
A49: ES-SAGUNTO | B49: Spain | C49: Europe | D49: Sagunto | E49: Saggas/Enagás | F49: onshore | G49: operational | H49: 8.8 | I49: 6.5 | J49: 600000 | K49: 2006-04-01 | L49: yes | M49: Enagás | N49: 2026-06-01
A50: TR-DORTYOL-FSRU | B50: Türkiye | C50: Europe | D50: Dörtyol FSRU | E50: BOTAS | F50: FSRU | G50: operational | H50: 7.4 | I50: 5.4 | J50: 170000 | K50: 2018-02-01 | L50: no | M50: BOTAS | N50: 2026-06-01
A51: TR-MARMARAEREGLISI | B51: Türkiye | C51: Europe | D51: Marmara Ereğlisi | E51: BOTAS | F51: onshore | G51: operational | H51: 8.2 | I51: 6 | J51: 255000 | K51: 1994-01-01 | L51: no | M51: BOTAS | N51: 2026-06-01
A52: GB-DRAGON | B52: United Kingdom | C52: Europe | D52: Dragon LNG | E52: Shell/Ancala | F52: onshore | G52: operational | H52: 8.4 | I52: 6.2 | J52: 320000 | K52: 2009-08-01 | L52: yes | M52: Dragon LNG | N52: 2026-06-01 | O52: Milford Haven
A53: GB-ISLEOFGRAIN | B53: United Kingdom | C53: Europe | D53: Isle of Grain | E53: National Grid Grain LNG | F53: onshore | G53: operational | H53: 19.5 | I53: 14.3 | J53: 1000000 | K53: 2005-07-01 | L53: yes | M53: National Grid | N53: 2026-06-01 | O53: UK's largest
A54: GB-SOUTHHOOK | B54: United Kingdom | C54: Europe | D54: South Hook | E54: QatarEnergy/ExxonMobil/TotalEnergies | F54: onshore | G54: operational | H54: 15.6 | I54: 11.5 | J54: 775000 | K54: 2009-03-01 | L54: yes | M54: South Hook LNG | N54: 2026-06-01 | O54: Milford Haven
A55: AR-ESCOBAR | B55: Argentina | C55: Latin America | D55: Escobar FSRU | E55: Excelerate/Enarsa | F55: FSRU | G55: operational | H55: 11 | I55: 8.1 | J55: 150000 | K55: 2011-06-01 | L55: no | M55: Excelerate | N55: 2026-06-01 | O55: Seasonal high winter use
A56: BR-GUANABARA | B56: Brazil | C56: Latin America | D56: Guanabara Bay FSRU | E56: Petrobras | F56: FSRU | G56: operational | H56: 11 | I56: 8.1 | J56: 170000 | K56: 2014-01-01 | L56: no | M56: Petrobras | N56: 2026-06-01 | O56: Replaced original FSRU
A57: BR-PECEM | B57: Brazil | C57: Latin America | D57: Pecem FSRU | E57: Petrobras | F57: FSRU | G57: operational | H57: 7 | I57: 5.1 | J57: 170000 | K57: 2008-12-01 | L57: no | M57: Petrobras | N57: 2026-06-01 | O57: Ceará
A58: MX-MANZANILLO | B58: Mexico | C58: North America | D58: Manzanillo | E58: KMS LNG (Mitsui/Samsung/KOGAS) | F58: onshore | G58: operational | H58: 4.4 | I58: 3.2 | J58: 300000 | K58: 2012-03-01 | L58: no | M58: KMS | N58: 2026-06-01
A59: SG-SLNG | B59: Singapore | C59: SE Asia | D59: Singapore LNG Terminal | E59: SLNG Corp | F59: onshore | G59: operational | H59: 9 | I59: 6.6 | J59: 800000 | K59: 2013-05-07 | L59: yes | M59: SLNG | N59: 2026-06-01 | O59: Expansion to 11+ BCm/y
A60: IN-DAHEJ | B60: India | C60: South Asia | D60: Dahej | E60: Petronet LNG | F60: onshore | G60: operational | H60: 23.8 | I60: 17.5 | J60: 648000 | K60: 2004-04-01 | L60: yes | M60: Petronet | N60: 2026-06-01 | O60: India's largest regas
A61: IN-DHAMRA | B61: India | C61: South Asia | D61: Dhamra | E61: Adani/TotalEnergies | F61: onshore | G61: operational | H61: 6.8 | I61: 5 | J61: 360000 | K61: 2024-04-01 | L61: no | M61: Adani | N61: 2026-06-01 | O61: Odisha; commissioned Apr 2024
A62: IN-ENNORE | B62: India | C62: South Asia | D62: Ennore | E62: IOCL/TIDCO | F62: onshore | G62: operational | H62: 6.8 | I62: 5 | J62: 360000 | K62: 2019-03-01 | L62: no | M62: IOCL | N62: 2026-06-01 | O62: Tamil Nadu
A63: IN-HAZIRA | B63: India | C63: South Asia | D63: Hazira | E63: Shell/TotalEnergies | F63: onshore | G63: operational | H63: 6.8 | I63: 5 | J63: 320000 | K63: 2005-04-01 | L63: no | M63: Shell | N63: 2026-06-01
A64: IN-KOCHI | B64: India | C64: South Asia | D64: Kochi | E64: Petronet LNG | F64: onshore | G64: operational | H64: 6.8 | I64: 5 | J64: 320000 | K64: 2013-08-01 | L64: no | M64: Petronet | N64: 2026-06-01 | O64: Underutilized; pipeline-constrained
A65: IN-MUNDRA | B65: India | C65: South Asia | D65: Mundra | E65: Adani/IOCL | F65: onshore | G65: operational | H65: 6.8 | I65: 5 | J65: 320000 | K65: 2020-04-01 | L65: no | M65: Adani | N65: 2026-06-01
A66: PK-PAKISTAN-GASPORT | B66: Pakistan | C66: South Asia | D66: Pakistan GasPort FSRU | E66: PGPL | F66: FSRU | G66: operational | H66: 5.5 | I66: 4 | J66: 170000 | K66: 2018-01-15 | L66: no | M66: PGPL | N66: 2026-06-01
A67: PK-PORT-QASIM | B67: Pakistan | C67: South Asia | D67: Port Qasim FSRU (Engro) | E67: Engro Elengy/ETPL | F67: FSRU | G67: operational | H67: 5.5 | I67: 4 | J67: 170000 | K67: 2015-03-28 | L67: no | M67: Engro | N67: 2026-06-01

Sheet Regasification — Upcoming
A1: Facility ID | B1: Country | C1: Region | D1: Facility | E1: Operator | F1: Type | G1: Status | H1: Send-out (Bcm/y) | I1: Send-out (MTPA) | J1: Storage (m³ LNG) | K1: Start | L1: Reload? | M1: Source | N1: Updated | O1: Notes
A2: CN-WENZHOU | B2: China | C2: East Asia | D2: Wenzhou | E2: CNOOC | F2: onshore | G2: construction | H2: 8.5 | I2: 6.3 | J2: 800000 | K2: 2026-09-30 | L2: yes | M2: CNOOC | N2: 2026-06-01 | O2: Phase 1 expected late 2026
A3: DE-STADE-ONSHORE | B3: Germany | C3: Europe | D3: Stade | E3: Hanseatic Energy Hub | F3: onshore | G3: construction | H3: 13.3 | I3: 9.8 | J3: 260000 | K3: 2027-06-30 | L3: yes | M3: HEH | N3: 2026-06-01 | O3: Replaces FSRU(s) when COD

Sheet Capacity Schedule
A1: Year | B1: Additions — operational record (MTPA) | C1: Additions — upcoming (MTPA) | D1: Total additions (MTPA) | E1: Cumulative since first year (MTPA)
A2: 1977 | B2: 22.5 | C2: 0 | D2: 22.5 | E2: 22.5
A3: 1983 | B3: 8.4 | C3: 0 | D3: 8.4 | E3: 30.9
A4: 1989 | B4: 5 | C4: 0 | D4: 5 | E4: 35.9
A5: 1992 | B5: 2.5 | C5: 0 | D5: 2.5 | E5: 38.4
A6: 1995 | B6: 9.6 | C6: 0 | D6: 9.6 | E6: 48
A7: 1997 | B7: 6.6 | C7: 0 | D7: 6.6 | E7: 54.6
A8: 1999 | B8: 13.1 | C8: 0 | D8: 13.1 | E8: 67.7
A9: 2002 | B9: 6.5 | C9: 0 | D9: 6.5 | E9: 74.2
A10: 2003 | B10: 11.2 | C10: 0 | D10: 11.2 | E10: 85.4
A11: 2004 | B11: 18.5 | C11: 0 | D11: 18.5 | E11: 103.9
A12: 2005 | B12: 25.8 | C12: 0 | D12: 25.8 | E12: 129.7
A13: 2007 | B13: 8.4 | C13: 0 | D13: 8.4 | E13: 138.1
... A36: 2031 | B36: 0 | C36: 9 | D36: 9 | E36: 597.48

Sheet Disruptions
A1: Facility ID | B1: Disruption ID | C1: Type | D1: Start | E1: End | F1: Impact (MTPA) | G1: Description | H1: Source | I1: Updated
A2: NO-SNOHVIT | B2: SNOHVIT-FIRE-2020 | C2: unplanned_outage | D2: 2020-09-28 | E2: 2022-06-02 | F2: 4 | G2: Equinor Hammerfest LNG fire 2020; ~20 months full outage; full restart June 2022 | H2: Equinor + GIIGNL | I2: 2026-06-01
A3: MZ-MOZAMBIQUE-LNG-T1 | B3: MZ-FORCE-MAJEURE-2021 | C3: force_majeure | D3: 2021-04-26 | E3: 2025-11-07 | F3: 6.44 | G3: TotalEnergies declared FM after Palma insurgent attack; FM formally lifted by consortium 2025-11-07; full restart announced Jan 29 2026; construction resumed | H3: TotalEnergies + GIIGNL; totalenergies.com Jan 2026 press release | I3: 2026-06-22
A4: MZ-MOZAMBIQUE-LNG-T2 | B4: MZ-FORCE-MAJEURE-2021 | C4: force_majeure | D4: 2021-04-26 | E4: 2025-11-07 | F4: 6.44 | G4: Same incident; FM lifted concurrently with T1 | H4: Same | I4: 2026-06-22
A5: AU-GORGON-T2 | B5: GORGON-T2-PROPANE-2021 | C5: maintenance | D5: 2021-05-01 | E5: 2021-08-15 | F5: 1.5 | G5: Propane line crack repair; extended unplanned maintenance | H5: Chevron + ICIS | I5: 2026-06-01
A6: US-FREEPORT-T1 | B6: FREEPORT-FIRE-2022 | C6: unplanned_outage | D6: 2022-06-08 | E6: 2023-02-13 | F6: 5 | G6: Quintana Island liquefaction plant explosion forced full shutdown June 2022; partial restart Feb 2023; full restoration mid-2023 | H6: Freeport LNG press releases + FERC + Platts LNG Daily | I6: 2026-06-01
A7: US-FREEPORT-T2 | B7: FREEPORT-FIRE-2022 | C7: unplanned_outage | D7: 2022-06-08 | E7: 2023-02-13 | F7: 5 | G7: Same incident — all three trains taken offline | H7: Freeport LNG press releases + FERC + Platts LNG Daily | I7: 2026-06-01
A8: US-FREEPORT-T3 | B8: FREEPORT-FIRE-2022 | C8: unplanned_outage | D8: 2022-06-08 | E8: 2023-02-13 | F8: 5 | G8: Same incident | H8: Freeport LNG press releases + FERC + Platts LNG Daily | I8: 2026-06-01
A9: EG-DAMIETTA | B9: EG-DOMESTIC-CURTAIL-2022 | C9: force_majeure | D9: 2022-07-01 | E9: 2024-09-01 | F9: 3 | G9: Egyptian government redirected gas to power generation amid domestic shortage; Damietta intermittent throughout 2022-2024 | H9: Eni + Argus | I9: 2026-06-01
A10: EG-IDKU-T1 | B10: EG-DOMESTIC-CURTAIL-2022 | C10: force_majeure | D10: 2022-07-01 | E10: 2024-09-01 | F10: 2 | G10: Same domestic curtailment; one train idled for periods | H10: Shell + Argus | I10: 2026-06-01
A11: RU-ARCTIC2-T1 | B11: ARCTIC2-SANCTIONS | C11: sanctions | D11: 2023-11-02 | F11: 5.3 | G11: US OFAC SDN designation Nov 2023; mothballed Oct 2024-Mar 2025 after ~10 unsold cargoes; deliveries to China began Aug 2025; 23 cargoes / 1.3 Mt delivered in 2025; realized throughput ~1.3 MTPA vs 6.6 MTPA nameplate; capacity_impact revised to 5.3 (= 6.6 - 1.3 realized); Arc7 tanker shortage remains primary constraint; TotalEnergies exit approved Jun 2026 | H11: US Treasury OFAC + Argus + Reuters + Platts LNG Daily; bairdmaritime.com Jan 2026; energyconnects.com Nov 2025; gcaptain.com Aug 2025; highnorthnews.com | I11: 2026-06-22
A12: RU-ARCTIC2-T2 | B12: ARCTIC2-T2-PAUSE | C12: delay | D12: 2024-01-01 | F12: 6.6 | G12: Tow to site delayed; LNG carriers under sanction; effective indefinite pause | H12: Argus + Reuters + Platts LNG Daily | I12: 2026-06-01
A13: RU-ARCTIC2-T3 | B13: ARCTIC2-T3-PAUSE | C13: delay | D13: 2024-01-01 | F13: 6.6 | G13: Construction halted at module yard; no realistic delivery before 2028 | H13: Argus + Reuters + Platts LNG Daily | I13: 2026-06-01
A14: US-GOLDENPASS-T1 | B14: GOLDENPASS-CONTRACTOR-2024 | C14: delay | D14: 2024-04-15 | E14: 2026-03-30 | F14: 5.2 | G14: Zachry bankruptcy filing forced contractor reshuffle; project pushed from 2024 to 2H 2026; resolved — first LNG achieved 2026-03-30; first cargo exported 2026-04-22 | H14: Reuters + SEC filings + Platts LNG Daily; eia.gov id=67564; energyconnects.com Apr 2026 | I14: 2026-06-22
A15: US-PLAQUEMINES-P1 | B15: PLAQUEMINES-OFFTAKE-DISPUTE | C15: delay | D15: 2024-06-01 | F15: 3 | G15: Venture Global commercial-ops dispute with long-term offtakers; cargoes sold at spot until contract activation; Phase 1 commercial deliveries now expected Q4 2026; BP won ICC arbitration finding VG breached COD obligations; Edison dispute settled Mar 2026; other cases ongoing | H15: Reuters + offtaker complaints + Platts LNG Daily; argusmedia.com; ogj.com; SEC 8-K VG 2026 | I15: 2026-06-22
A16: MR-SN-TORTUE | B16: TORTUE-RAMP-2025 | C16: ramp_slippage | D16: 2025-02-15 | E16: 2025-07-01 | F16: 1 | G16: Phase 1 first cargo Feb 2025 after multi-year delays; ramped to ~90% of nameplate (~2.4 MTPA) by mid-2025; ramp slippage period effectively closed | H16: BP press releases + Platts LNG Daily; kosmosenergy.com; offshore-technology.com | I16: 2026-06-22
A17: US-CORPUSCHRISTI-CC3 | B17: CC3-RAMP-2025 | C17: ramp_slippage | D17: 2025-03-01 | F17: 1.5 | G17: Stage 3 commissioning across 7 midscale trains progressing slower than initial schedule; 6 of 7 trains producing LNG by May 2026; T7 expected fall 2026; ramp ongoing | H17: Cheniere Q4 2024 earnings + Platts LNG Daily; lngprime.com; naturalgasintel.com May 2026 | I17: 2026-06-22
A18: QA-QATARENERGY-NFE-T1 | B18: NFE-RAMP-SLIP-2026 | C18: ramp_slippage | D18: 2026-01-01 | F18: 2 | G18: COD slipped from initial 2026-Q1 target to Q3 2026; first LNG achieved Nov 2025; pre-commissioning ongoing; targeting mid-2026 COD; partial revenue impact ongoing | H18: QatarEnergy + IGU 2025 update + Platts LNG Daily; mees.com Dec 2025; lngindustry.com May 2025 | I18: 2026-06-22
A19: AU-WHEATSTONE-T1 | B19: WHEATSTONE-CYCLONE-NARELLE-2026 | C19: unplanned_outage | D19: 2026-03-25 | E19: 2026-04-23 | F19: 4.45 | G19: Tropical Cyclone Narelle damaged several hundred air-cooled heat exchangers (fin fans); both Wheatstone LNG trains taken offline; domestic gas restored ~1 week post-event; T1 back at full rates mid-April; full production restored 2026-04-23 | H19: pgjonline.com Apr 2026; lngprime.com; energynow.com Apr 2026; miningweekly.com 2026-03-30 | I19: 2026-06-22
A20: AU-WHEATSTONE-T2 | B20: WHEATSTONE-CYCLONE-NARELLE-2026 | C20: unplanned_outage | D20: 2026-03-25 | E20: 2026-04-23 | F20: 4.45 | G20: Same incident; T2 also offline; full LNG production confirmed restored 2026-04-23 per Chevron Australia | H20: pgjonline.com Apr 2026; chevron australia statement | I20: 2026-06-22
A21: US-FREEPORT-T2 | B21: FREEPORT-MAINT-2026 | C21: maintenance | D21: 2026-05-13 | E21: 2026-06-10 | F21: 5.1 | G21: Planned spring maintenance; Freeport T2 taken offline May 13 2026; followed unplanned outage early May; all three trains returned to service by early June 2026; three cancelled cargoes | H21: energynow.com May 2026; naturalgasintel.com; pgjonline.com Jun 2026 | I21: 2026-06-22

Sheet Sources
A1: Source | B1: Rows referencing
A2: QatarEnergy | B2: 11
A3: Cheniere 10-K | B3: 8
A4: Shell | B4: 6
A5: Petronas | B5: 6
A6: Woodside | B6: 5
A7: Chevron | B7: 5
A8: NLNG | B8: 5
A9: Enagás | B9: 5
A10: Novatek | B10: 4
A11: Atlantic LNG | B11: 4
A12: KOGAS | B12: 4
A13: CNOOC | B13: 4
... A116: energynow.com May 2026; naturalgasintel.com; pgjonline.com Jun 2026 | B116: 1
